lat_epig/__init__.py
lat_epig/date_parse.py
lat_epig/findUnknownPartners.py
lat_epig/interactive_map.py
lat_epig/interactive_map_interface.py
lat_epig/interface.py
lat_epig/make_map.py
lat_epig/map_interface.py
lat_epig/parse.py
lat_epig/partner_parser.py
lat_epig/scalebar.py
lat_epig/test_dates.py
lat_epig/test_inscriptions.py
lat_epig/test_language.py
lat_epig/test_scrape.py
lat_epig/text_parse.py
lat_epig-2.0.2.dist-info/LICENSE
lat_epig-2.0.2.dist-info/METADATA
lat_epig-2.0.2.dist-info/WHEEL
lat_epig-2.0.2.dist-info/top_level.txt
lat_epig-2.0.2.dist-info/RECORD
