Metadata-Version: 2.1
Name: lat-epig
Version: 2.0.2
Summary: This programme extracts the output of a search query from the [Epigraphik-Datenbank  Clauss / Slaby (EDCS)](http://www.manfredclauss.de/) in a reproducible manner and saves it as a TSV file. The output can be also plotted to a map of the Roman Empire, along with the system of Roman Provinces, roads, and cities.
Home-page: https://github.com/mqAncientHistory/Lat-Epig
Author: Brian Ballsun-Stanton
Author-email: brian.ballsun-stanton@mq.edu.au
License: GPLv3
Project-URL: Documentation, https://github.com/mqAncientHistory/Lat-Epig/wiki
Project-URL: Source, https://github.com/mqAncientHistory/Lat-Epig
Project-URL: Tracker, https://github.com/mqAncientHistory/Lat-Epig/issues
Platform: UNKNOWN
Classifier: Programming Language :: Python :: 3
Classifier: License :: OSI Approved :: GNU General Public License v3 or later (GPLv3+)
Classifier: Operating System :: POSIX :: Linux
Classifier: Development Status :: 4 - Beta
Classifier: Framework :: Jupyter
Classifier: Intended Audience :: Education
Classifier: Intended Audience :: Science/Research
Requires-Python: >=3.8
License-File: LICENSE
Requires-Dist: setuptools
Requires-Dist: wheel
Requires-Dist: numpy
Requires-Dist: cython
Requires-Dist: pyshp
Requires-Dist: mechanicalsoup
Requires-Dist: bs4
Requires-Dist: tkinter
Requires-Dist: pprint
Requires-Dist: clint
Requires-Dist: yaspingeopandas
Requires-Dist: frictionless
Requires-Dist: pandas
Requires-Dist: geoplot
Requires-Dist: shapely
Requires-Dist: contextily
Requires-Dist: cartopy
Requires-Dist: matplotlib
